coindy/__init__.py
coindy/__main__.py
coindy/__pycache__/__init__.cpython-39.pyc
coindy/__pycache__/__main__.cpython-39.pyc
coindy/base_classes/__init__.py
coindy/base_classes/progress_worker.py
coindy/base_classes/__pycache__/__init__.cpython-39.pyc
coindy/base_classes/__pycache__/progress_worker.cpython-39.pyc
coindy/sde/__init__.py
coindy/sde/sde_classes.py
coindy/sde/sde_demo.py
coindy/sde/__pycache__/__init__.cpython-39.pyc
coindy/sde/__pycache__/sde_classes.cpython-39.pyc
coindy/sde/__pycache__/sde_demo.cpython-39.pyc
coindy/sde/tests/__init__.py
coindy/sde/tests/test_sde_model.py
coindy/sde/tests/__pycache__/__init__.cpython-39.pyc
coindy/sde/tests/__pycache__/test_sde_model.cpython-39-pytest-7.1.2.pyc
coindy/utils/__init__.py
coindy/utils/console_utils.py
coindy/utils/ito_utils.py
coindy/utils/matrix_utils.py
coindy/utils/simulation_utils.py
coindy/utils/__pycache__/__init__.cpython-39.pyc
coindy/utils/__pycache__/console_utils.cpython-39.pyc
coindy/utils/__pycache__/ito_utils.cpython-39.pyc
coindy/utils/__pycache__/matrix_utils.cpython-39.pyc
coindy/utils/__pycache__/simulation_utils.cpython-39.pyc
coindy/utils/__pycache__/test_ito_utils.cpython-39-pytest-7.1.2.pyc
coindy/utils/__pycache__/test_matrix_utils.cpython-39-pytest-7.1.2.pyc
coindy/utils/__pycache__/test_simulation_utils.cpython-39-pytest-7.1.2.pyc
coindy/utils/tests/__init__.py
coindy/utils/tests/test_ito_utils.py
coindy/utils/tests/test_matrix_utils.py
coindy/utils/tests/test_simulation_utils.py
coindy/utils/tests/.pytest_cache/.gitignore
coindy/utils/tests/.pytest_cache/CACHEDIR.TAG
coindy/utils/tests/.pytest_cache/README.md
coindy/utils/tests/.pytest_cache/v/cache/lastfailed
coindy/utils/tests/.pytest_cache/v/cache/nodeids
coindy/utils/tests/.pytest_cache/v/cache/stepwise
coindy/utils/tests/__pycache__/__init__.cpython-39.pyc
coindy/utils/tests/__pycache__/test_ito_utils.cpython-39-pytest-7.1.2.pyc
coindy/utils/tests/__pycache__/test_matrix_utils.cpython-39-pytest-7.1.2.pyc
coindy-0.0.1.dist-info/LICENSE
coindy-0.0.1.dist-info/METADATA
coindy-0.0.1.dist-info/WHEEL
coindy-0.0.1.dist-info/entry_points.txt
coindy-0.0.1.dist-info/top_level.txt
coindy-0.0.1.dist-info/RECORD
