Metadata-Version: 2.1
Name: coindy
Version: 0.0.1
Summary: A library for computing simulations of stochastic differential equations in symbolic form
Author-email: Paul Mucchielli <paulmucc@gmail.com>
License: GPL-3.0-only
Project-URL: Homepage, https://github.com/paulmuc/coindy
Keywords: SDE,stochastic differential equations,nonlinear dynamics
Classifier: Programming Language :: Python
Classifier: Programming Language :: Python :: 3
Classifier: Development Status :: 1 - Planning
Classifier: Intended Audience :: Science/Research
Classifier: License :: OSI Approved :: GNU General Public License (GPL)
Classifier: Operating System :: OS Independent
Classifier: Topic :: Scientific/Engineering
Requires-Python: >=3.9
License-File: LICENSE
Requires-Dist: matplotlib (>=3.4.2)
Requires-Dist: numpy (>=1.20.2)
Requires-Dist: rich (>=12.4.4)
Requires-Dist: sympy (>=1.8)
Requires-Dist: tomli ; python_version < "3.11"
Provides-Extra: dev
Requires-Dist: pytest ; extra == 'dev'
